lantvh.py
lantvh_test-0.1.dist-info/METADATA
lantvh_test-0.1.dist-info/WHEEL
lantvh_test-0.1.dist-info/entry_points.txt
lantvh_test-0.1.dist-info/top_level.txt
lantvh_test-0.1.dist-info/RECORD
