Metadata-Version: 2.1
Name: lantvh-test
Version: 0.1
Summary: SDK example
Author: lantvh
Author-email: lantvh@vpi.pvn.vn
Requires-Dist: pandas (>=1.3.0)
